nextstep/GridSearch.py
nextstep/__init__.py
nextstep/feature_engineering.py
nextstep/feature_selection.py
nextstep/getData/__init__.py
nextstep/getData/oil.py
nextstep/getData/weather.py
nextstep/model/GridSearch.py
nextstep/model/XGboost.py
nextstep/model/__init__.py
nextstep/model/adaboost.py
nextstep/model/arima.py
nextstep/model/base_model.py
nextstep/model/lstm.py
nextstep/model/random_forest.py
nextstep/model/sarima.py
nextstep-0.0.19.dist-info/METADATA
nextstep-0.0.19.dist-info/WHEEL
nextstep-0.0.19.dist-info/top_level.txt
nextstep-0.0.19.dist-info/RECORD
