Metadata-Version: 2.1
Name: nextstep
Version: 0.0.19
Summary: USEP price prediction
Home-page: https://github.com/YangYuesong0323/nextstep
Author: Yang Yuesong
Author-email: yangyuesongyys@gmail.com
License: UNKNOWN
Platform: UNKNOWN
Requires-Python: >=3.6
Requires-Dist: wwo-hist (==0.0.4)
Requires-Dist: tensorflow (==2.1.0)
Requires-Dist: statsmodels (==0.11.0)
Requires-Dist: dataflows (==0.0.71)
Requires-Dist: Keras (==2.3.1)
Requires-Dist: pandas (==1.0.1)
Requires-Dist: numpy (==1.18.1)
Requires-Dist: scikit-learn (==0.22.1)
Requires-Dist: lightgbm (==2.3.1)
Requires-Dist: matplotlib (==3.0.3)
